modelbusinesscards/__init__.py
modelbusinesscards/__main__.py
modelbusinesscards/entities.py
modelbusinesscards/main.py
modelbusinesscards/parser.py
modelbusinesscards/writer.py
modelbusinesscards-0.0.3.dist-info/LICENSE
modelbusinesscards-0.0.3.dist-info/METADATA
modelbusinesscards-0.0.3.dist-info/WHEEL
modelbusinesscards-0.0.3.dist-info/top_level.txt
modelbusinesscards-0.0.3.dist-info/RECORD
