Metadata-Version: 2.1
Name: modelbusinesscards
Version: 0.0.3
Summary: Generating documentation of AI model usage to increase visibility and safety
Home-page: https://github.com/youmustfight/model-business-cards
License: MIT
License-File: LICENSE
